[
  {
    "id": "version-1782522936635",
    "createdAt": "2026-06-27T01:15:36.372Z",
    "actor": "admin-key",
    "message": "Update Travel Journal",
    "summary": "Update Travel Journal"
  },
  {
    "id": "version-1782492165875",
    "createdAt": "2026-06-26T16:42:45.593Z",
    "actor": "admin-key",
    "message": "Update Travel Journal",
    "summary": "Update Travel Journal"
  },
  {
    "id": "version-1782490798521",
    "createdAt": "2026-06-26T16:19:58.128Z",
    "actor": "admin-key",
    "message": "Update Travel Journal",
    "summary": "Update Travel Journal"
  },
  {
    "id": "version-1782482321316",
    "createdAt": "2026-06-26T13:58:41.114Z",
    "actor": "admin-key",
    "message": "Update Travel Journal",
    "summary": "Update Travel Journal"
  }
]